MANIFEST.in
README.md
setup.py
WaveDefense/__init__.py
WaveDefense.egg-info/PKG-INFO
WaveDefense.egg-info/SOURCES.txt
WaveDefense.egg-info/dependency_links.txt
WaveDefense.egg-info/requires.txt
WaveDefense.egg-info/top_level.txt
WaveDefense/envs/__init__.py
WaveDefense/envs/black.jpg
WaveDefense/envs/player.png
WaveDefense/envs/wave_defense.py
WaveDefense/envs/wave_defense_tabular.py
WaveDefense/envs/prefabs/__init__.py
WaveDefense/envs/prefabs/bullet.py
WaveDefense/envs/prefabs/enemy_spawner.py
WaveDefense/envs/prefabs/normal_enemy.py
WaveDefense/envs/prefabs/player.py