Metadata-Version: 2.1
Name: WaveDefense
Version: 0.4
Summary: UNKNOWN
Home-page: UNKNOWN
Author: Roger Creus
Author-email: creus99@protonmail.com
License: UNKNOWN
Platform: UNKNOWN
